supertonic/__init__.py
supertonic/cli.py
supertonic/config.py
supertonic/core.py
supertonic/loader.py
supertonic/pipeline.py
supertonic/utils.py
supertonic-1.1.1.dist-info/licenses/LICENSE
supertonic-1.1.1.dist-info/METADATA
supertonic-1.1.1.dist-info/WHEEL
supertonic-1.1.1.dist-info/entry_points.txt
supertonic-1.1.1.dist-info/top_level.txt
supertonic-1.1.1.dist-info/RECORD
