Metadata-Version: 2.4
Name: supertonic
Version: 1.1.1
Summary: High-quality Text-to-Speech synthesis with ONNX Runtime
Author-email: "Kim, Hyeongju" <hyeongju@supertone.ai>, "Yu, Yechan" <ato@supertone.ai>, "Lee, Juheon" <juheon@supertone.ai>
Maintainer-email: "Supertone Inc." <contact@supertone.ai>
License: MIT
Project-URL: Homepage, https://github.com/supertone-inc/supertonic-python-package
Project-URL: Repository, https://github.com/supertone-inc/supertonic-python-package
Project-URL: Documentation, https://github.com/supertone-inc/supertonic-python-package/tree/main/docs
Project-URL: Issues, https://github.com/supertone-inc/supertonic-python-package/issues
Project-URL: Demo, https://huggingface.co/spaces/Supertone/supertonic
Project-URL: Model Hub, https://huggingface.co/Supertone/supertonic
Keywords: tts,text-to-speech,speech-synthesis,onnx,deep-learning,audio,voice-synthesis,neural-tts,on-device
Classifier: Development Status :: 4 - Beta
Classifier: Intended Audience :: Developers
Classifier: Intended Audience :: Science/Research
Classifier: License :: OSI Approved :: MIT License
Classifier: Operating System :: OS Independent
Classifier: Programming Language :: Python :: 3
Classifier: Programming Language :: Python :: 3.9
Classifier: Programming Language :: Python :: 3.10
Classifier: Programming Language :: Python :: 3.11
Classifier: Programming Language :: Python :: 3.12
Classifier: Topic :: Scientific/Engineering :: Artificial Intelligence
Classifier: Topic :: Multimedia :: Sound/Audio :: Speech
Classifier: Topic :: Software Development :: Libraries :: Python Modules
Classifier: Typing :: Typed
Requires-Python: >=3.9
License-File: LICENSE
Requires-Dist: onnxruntime>=1.10.0
Requires-Dist: numpy<2.0,>=1.21.0
Requires-Dist: soundfile>=0.10.0
Requires-Dist: huggingface-hub>=0.10.0
Provides-Extra: playback
Requires-Dist: sounddevice>=0.4.0; extra == "playback"
Provides-Extra: dev
Requires-Dist: pytest>=7.0; extra == "dev"
Requires-Dist: pytest-cov>=4.1.0; extra == "dev"
Requires-Dist: black>=23.0; extra == "dev"
Requires-Dist: ruff>=0.1.0; extra == "dev"
Requires-Dist: build>=1.0.0; extra == "dev"
Requires-Dist: twine>=4.0.0; extra == "dev"
Dynamic: license-file
